Metadata-Version: 2.1
Name: show-contests
Version: 1.0
Summary: A basic command line tool to show the upcoming competitive programming contests
Home-page: https://github.com/singlamohit1/show-contests
Author: singlamohit1
Author-email: singlamohit98@gmail.com
License: Apache 2.0
Platform: UNKNOWN
